{
    "boxShadow": "{{appsmith.theme.boxShadow.appBoxShadow}}",
    "widgetName": "Container1Copy6Copy3",
    "borderColor": "#fde047",
    "isCanvas": true,
    "dynamicPropertyPathList": [{"key": "isVisible"}],
    "displayName": "Container",
    "iconSVG": "/static/media/icon.1977dca3370505e2db3a8e44cfd54907.svg",
    "searchTags": [
        "div",
        "parent",
        "group"
    ],
    "topRow": 21,
    "bottomRow": 38,
    "parentRowSpace": 10,
    "type": "CONTAINER_WIDGET",
    "hideCard": false,
    "animateLoading": true,
    "parentColumnSpace": 6.53125,
    "dynamicTriggerPathList": [],
    "leftColumn": 32,
    "dynamicBindingPathList": [
        {"key": "borderRadius"},
        {"key": "boxShadow"},
        {"key": "isVisible"}
    ],
    "children": [{
        "boxShadow": "none",
        "widgetName": "Canvas3Copy6Copy3",
        "displayName": "Canvas",
        "topRow": 0,
        "bottomRow": 160,
        "parentRowSpace": 1,
        "type": "CANVAS_WIDGET",
        "canExtend": false,
        "hideCard": true,
        "minHeight": 400,
        "parentColumnSpace": 1,
        "leftColumn": 0,
        "dynamicBindingPathList": [
            {"key": "borderRadius"},
            {"key": "accentColor"}
        ],
        "key": "8kwk9ynfmd",
        "isDeprecated": false,
        "rightColumn": 156.75,
        "detachFromLayout": true,
        "widgetId": "5whhwcp60a",
        "accentColor": "{{appsmith.theme.colors.primaryColor}}",
        "containerStyle": "none",
        "isVisible": true,
        "version": 1,
        "parentId": "iek01xxxhr",
        "renderMode": "CANVAS",
        "isLoading": false,
        "borderRadius": "{{appsmith.theme.borderRadius.appBorderRadius}}"
    }],
    "borderWidth": "3",
    "key": "eey0zbce6y",
    "backgroundColor": "#FFFFFF",
    "isDeprecated": false,
    "rightColumn": 64,
    "dynamicHeight": "FIXED",
    "widgetId": "iek01xxxhr",
    "containerStyle": "card",
    "isVisible": "{{appsmith.store.player4_active}}",
    "version": 1,
    "parentId": "0",
    "renderMode": "CANVAS",
    "isLoading": false,
    "borderRadius": "{{appsmith.theme.borderRadius.appBorderRadius}}",
    "maxDynamicHeight": 9000,
    "minDynamicHeight": 4
}